izihawa_utils/__init__.py
izihawa_utils/coding.py
izihawa_utils/common.py
izihawa_utils/env.py
izihawa_utils/exceptions.py
izihawa_utils/file.py
izihawa_utils/importlib.py
izihawa_utils/itertools.py
izihawa_utils/json.py
izihawa_utils/pb_to_json.py
izihawa_utils/podolsky_encoding.py
izihawa_utils/random.py
izihawa_utils/tskv.py
izihawa_utils-1.2.4.dist-info/LICENSE
izihawa_utils-1.2.4.dist-info/METADATA
izihawa_utils-1.2.4.dist-info/WHEEL
izihawa_utils-1.2.4.dist-info/RECORD
